AUTHORS.rst
CHANGELOG.rst
LICENSE
MANIFEST.in
README.rst
setup.py
jmbo_paste/__init__.py
jmbo_paste/templates.py
jmbo_paste.egg-info/PKG-INFO
jmbo_paste.egg-info/SOURCES.txt
jmbo_paste.egg-info/dependency_links.txt
jmbo_paste.egg-info/entry_points.txt
jmbo_paste.egg-info/not-zip-safe
jmbo_paste.egg-info/requires.txt
jmbo_paste.egg-info/top_level.txt
jmbo_paste/config/__init__.py
jmbo_paste/config/chart_urlconf_additions
jmbo_paste/config/ckeditor_urlconf_additions
jmbo_paste/config/competition_urlconf_additions
jmbo_paste/config/contact_urlconf_additions
jmbo_paste/config/event_urlconf_additions
jmbo_paste/config/gallery_urlconf_additions
jmbo_paste/config/generic_urlconf_additions
jmbo_paste/config/googlesearch_urlconf_additions
jmbo_paste/config/likes_urlconf_additions
jmbo_paste/config/music_urlconf_additions
jmbo_paste/config/object_tools_urlconf_additions
jmbo_paste/config/profile_model_additions
jmbo_paste/config/richcomments_urlconf_additions
jmbo_paste/config/show_urlconf_additions
jmbo_paste/templates/jmbo_project/bootstrap.py
jmbo_paste/templates/jmbo_project/buildout.cfg_tmpl
jmbo_paste/templates/jmbo_project/production.cfg_tmpl
jmbo_paste/templates/jmbo_project/qa.cfg_tmpl
jmbo_paste/templates/jmbo_project/staging.cfg_tmpl
jmbo_paste/templates/jmbo_project/buildout_templates/nginx.conf
jmbo_paste/templates/jmbo_project/buildout_templates/nginx.ssl.conf
jmbo_paste/templates/jmbo_project/buildout_templates/supervisor.uwsgi
jmbo_paste/templates/jmbo_project/log/nginx/+hostname+/access.log
jmbo_paste/templates/jmbo_project/log/nginx/+hostname+/error.log
jmbo_paste/templates/jmbo_project/log/nginx/+hostname_staging+/access.log
jmbo_paste/templates/jmbo_project/log/nginx/+hostname_staging+/error.log
jmbo_paste/templates/jmbo_project/media/uploads/.placeholder
jmbo_paste/templates/jmbo_project/src/+project+/MANIFEST.in_tmpl
jmbo_paste/templates/jmbo_project/src/+project+/README.rst
jmbo_paste/templates/jmbo_project/src/+project+/setup.py_tmpl
jmbo_paste/templates/jmbo_project/src/+project+/+project+/__init__.py
jmbo_paste/templates/jmbo_project/src/+project+/+project+/dev_settings.py_tmpl
jmbo_paste/templates/jmbo_project/src/+project+/+project+/gizmos.py
