Metadata-Version: 1.0
Name: jmbo-paste
Version: 0.1.7
Summary: Python Paste templates creating Jmbo Buildout environments.
Home-page: https://github.com/praekelt/jmbo-paste
Author: Praekelt Foundation
Author-email: dev@praekelt.com
License: BSD
Platform: UNKNOWN
Classifier: Programming Language :: Python
Classifier: License :: OSI Approved :: BSD License
Classifier: Development Status :: 4 - Beta
Classifier: Operating System :: OS Independent
Classifier: Framework :: Paste
Classifier: Intended Audience :: Developers
Classifier: Topic :: Internet :: WWW/HTTP :: Dynamic Content
